Labs5stYear/hardware_impl_crypto/lab2/my/rtl/mealy.sv
module mealy2 (
    input  logic       rst,
    input  logic       clk,
    input  logic [1:0] i,
    output logic [1:0] y
);
    parameter [1:0] S0 = 2'b00;
    parameter [1:0] S1 = 2'b01;
    parameter [1:0] S2 = 2'b10;
    parameter [1:0] S3 = 2'b11;

    logic [1:0] state, next_state;

    always @(*) begin
        case (state)
            S0: case (i)
                    2'b00: begin next_state = S0; y = 2'b01; end
                    2'b01: begin next_state = S1; y = 2'b00; end
                    2'b10: begin next_state = S2; y = 2'b11; end
                    default: begin next_state = S3; y = 2'b10; end
                endcase
            S1: case (i)
                    2'b00: begin next_state = S1; y = 2'b11; end
                    2'b01: begin next_state = S2; y = 2'b10; end
                    2'b10: begin next_state = S3; y = 2'b01; end
                    default: begin next_state = S0; y = 2'b00; end
                endcase
            S2: case (i)
                    2'b00: begin next_state = S2; y = 2'b10; end
                    2'b01: begin next_state = S3; y = 2'b01; end
                    2'b10: begin next_state = S0; y = 2'b00; end
                    default: begin next_state = S1; y = 2'b11; end
                endcase
            S3: case (i)
                    2'b00: begin next_state = S3; y = 2'b00; end
                    2'b01: begin next_state = S0; y = 2'b11; end
                    2'b10: begin next_state = S1; y = 2'b10; end
                    default: begin next_state = S2; y = 2'b01; end
                endcase
            default: begin next_state = S0; y = 2'b00; end
        endcase
    end

    always @(posedge clk) begin
        if (rst) state <= S0;
        else     state <= next_state;
    end
endmodule

Labs5stYear/hardware_impl_crypto/lab2/my/sim/tb_mealy.sv
`timescale 1ns / 1ns

module tb_mealy2;
  parameter TRANSITIONS = 22;

  logic rst = 0;
  logic clk = 1;
  logic [1:0] i;
  logic [1:0] y;

  logic [1:0] test_inputs [TRANSITIONS];
  logic [1:0] expected_outputs [TRANSITIONS];

  initial begin
    $dumpfile("work/mealy2.vcd");
    $dumpvars(0, tb_mealy2);
  end

  initial begin
    // Подаём 00,01,10,11 циклом
    test_inputs[0]  = 2'b00; expected_outputs[0]  = 2'b01; // S0 - S0
    test_inputs[1]  = 2'b01; expected_outputs[1]  = 2'b00; // S0 - S1
    test_inputs[2]  = 2'b10; expected_outputs[2]  = 2'b01; // S1 - S3
    test_inputs[3]  = 2'b11; expected_outputs[3]  = 2'b01; // S3 - S2
    test_inputs[4]  = 2'b00; expected_outputs[4]  = 2'b10; // S2 - S2
    test_inputs[5]  = 2'b01; expected_outputs[5]  = 2'b01; // S2 - S3
    test_inputs[6]  = 2'b10; expected_outputs[6]  = 2'b10; // S3 - S1
    test_inputs[7]  = 2'b11; expected_outputs[7]  = 2'b00; // S1 - S0
    test_inputs[8]  = 2'b01; expected_outputs[8]  = 2'b00; // S0 - S1
    test_inputs[9]  = 2'b00; expected_outputs[9]  = 2'b11; // S1 - S1
    test_inputs[10] = 2'b11; expected_outputs[10] = 2'b00; // S1 - S0
    test_inputs[11] = 2'b01; expected_outputs[11] = 2'b00; // S0 - S1
    test_inputs[12] = 2'b11; expected_outputs[12] = 2'b00; // S1 - S0
    test_inputs[13] = 2'b11; expected_outputs[13] = 2'b10; // S0 - S3
    test_inputs[14] = 2'b10; expected_outputs[14] = 2'b10; // S3 - S1
    test_inputs[15] = 2'b01; expected_outputs[15] = 2'b10; // S1 - S2
    test_inputs[16] = 2'b11; expected_outputs[16] = 2'b11; // S2 - S1
    test_inputs[17] = 2'b10; expected_outputs[17] = 2'b01; // S1 - S3
    test_inputs[18] = 2'b00; expected_outputs[18] = 2'b00; // S3 - S3
    test_inputs[19] = 2'b01; expected_outputs[19] = 2'b11; // S3 - S0
    test_inputs[20] = 2'b10; expected_outputs[20] = 2'b11; // S0 - S2
    test_inputs[21] = 2'b10; expected_outputs[21] = 2'b00; // S2 - S0
    
    @(posedge clk);
    rst = 1'b1;
    @(posedge clk);
    rst = 1'b0;

    for (int idx = 0; idx < TRANSITIONS; idx++) begin
      i = test_inputs[idx];
      @(posedge clk);
      $display("Test %2d: i=%2b, y=%2b, expected=%2b",
               idx, test_inputs[idx], y, expected_outputs[idx]);
      assert (y == expected_outputs[idx])
      else $error($sformatf("Wrong output on test vector %0d: i=%2b, expected=%2b, got=%2b",
                            idx, test_inputs[idx], expected_outputs[idx], y));
    end

    $finish;
  end

  always #5 clk = ~clk;

  mealy2 dut (
    .rst(rst),
    .clk(clk),
    .i(i),
    .y(y)
  );
endmodule

Labs5stYear/hardware_impl_crypto/lab2/my/sim/work/mealy2.vcd
$date
	Fri Oct 31 13:50:56 2025
$end
$version
	Icarus Verilog
$end
$timescale
	1ns
$end
$scope module tb_mealy2 $end
$var wire 2 ! y [1:0] $end
$var parameter 32 " TRANSITIONS $end
$var reg 1 # clk $end
$var reg 2 $ i [1:0] $end
$var reg 1 % rst $end
$scope module dut $end
$var wire 1 # clk $end
$var wire 2 & i [1:0] $end
$var wire 1 % rst $end
$var parameter 2 ' S0 $end
$var parameter 2 ( S1 $end
$var parameter 2 ) S2 $end
$var parameter 2 * S3 $end
$var reg 2 + next_state [1:0] $end
$var reg 2 , state [1:0] $end
$var reg 2 - y [1:0] $end
$upscope $end
$scope begin $ivl_for_loop0 $end
$var integer 32 . idx [31:0] $end
$upscope $end
$upscope $end
$enddefinitions $end
$comment Show the parameter values. $end
$dumpall
b11 *
b10 )
b1 (
b0 '
b10110 "
$end
#0
$dumpvars
b0 .
bx -
bx ,
bx +
bx &
0%
bx $
1#
bx !
$end
#5
0#
#10
b10 !
b10 -
b11 +
b0 ,
1%
1#
#15
0#
#20
b1 !
b1 -
b0 +
b0 $
b0 &
0%
1#
#25
0#
#30
b0 !
b0 -
b1 +
b1 $
b1 &
b1 .
1#
#35
0#
#40
b1 ,
b1 !
b1 -
b11 +
b10 $
b10 &
b10 .
1#
#45
0#
#50
b11 ,
b1 !
b1 -
b10 +
b11 $
b11 &
b11 .
1#
#55
0#
#60
b10 ,
b10 !
b10 -
b10 +
b0 $
b0 &
b100 .
1#
#65
0#
#70
b1 !
b1 -
b11 +
b1 $
b1 &
b101 .
1#
#75
0#
#80
b11 ,
b10 !
b10 -
b1 +
b10 $
b10 &
b110 .
1#
#85
0#
#90
b1 ,
b0 !
b0 -
b0 +
b11 $
b11 &
b111 .
1#
#95
0#
#100
b0 ,
b0 !
b0 -
b1 +
b1 $
b1 &
b1000 .
1#
#105
0#
#110
b1 ,
b11 !
b11 -
b1 +
b0 $
b0 &
b1001 .
1#
#115
0#
#120
b0 !
b0 -
b0 +
b11 $
b11 &
b1010 .
1#
#125
0#
#130
b0 ,
b0 !
b0 -
b1 +
b1 $
b1 &
b1011 .
1#
#135
0#
#140
b1 ,
b0 !
b0 -
b0 +
b11 $
b11 &
b1100 .
1#
#145
0#
#150
b10 !
b10 -
b11 +
b0 ,
b1101 .
1#
#155
0#
#160
b11 ,
b10 !
b10 -
b1 +
b10 $
b10 &
b1110 .
1#
#165
0#
#170
b1 ,
b10 !
b10 -
b10 +
b1 $
b1 &
b1111 .
1#
#175
0#
#180
b10 ,
b11 !
b11 -
b1 +
b11 $
b11 &
b10000 .
1#
#185
0#
#190
b1 ,
b1 !
b1 -
b11 +
b10 $
b10 &
b10001 .
1#
#195
0#
#200
b11 ,
b0 !
b0 -
b11 +
b0 $
b0 &
b10010 .
1#
#205
0#
#210
b11 !
b11 -
b0 +
b1 $
b1 &
b10011 .
1#
#215
0#
#220
b0 ,
b11 !
b11 -
b10 +
b10 $
b10 &
b10100 .
1#
#225
0#
#230
b0 !
b0 -
b0 +
b10 ,
b10101 .
1#
#235
0#
#240
b11 !
b11 -
b10 +
b0 ,
b10110 .
1#
