Labs5stYear/hardware_impl_crypto/lab2/semen/rtl/automata.sv
module automata (
    input logic rst,
    input logic clk,
    input logic [1:0] i,
    output logic [1:0] y
);
    parameter [1:0] S0 = 2'b00, S1 = 2'b01, S2 = 2'b10, S3 = 2'b11;
    logic [1:0] state, next_state;

    always @(*) begin
        case(state)
            S0:
                if (i == 2'b00) 
                    next_state = S0;
                else if (i == 2'b01)
                    next_state = S1;
                else if (i == 2'b10)
                    next_state = S2;
                else 
                    next_state = S3;

            S1:
                if (i == 2'b00) 
                    next_state = S0;
                else if (i == 2'b01)
                    next_state = S1;
                else if (i == 2'b10)
                    next_state = S2;
                else 
                    next_state = S3;

            S2:
                if (i == 2'b00) 
                    next_state = S0;
                else if (i == 2'b01)
                    next_state = S1;
                else if (i == 2'b10)
                    next_state = S2;
                else 
                    next_state = S3;

            S3:
                if (i == 2'b00) 
                    next_state = S0;
                else if (i == 2'b01)
                    next_state = S1;
                else if (i == 2'b10)
                    next_state = S2;
                else 
                    next_state = S3;

            default: next_state = S0;
        endcase
    end

    always @(posedge clk) begin
        if (rst) state <= S0;
        else     state <= next_state;
    end
    // Автомат Мили: выход зависит от текущего состояния и входа
    // Нетривиальная функция выхода: XOR состояния и входа
    assign y = state ^ i;
endmodule

Labs5stYear/hardware_impl_crypto/lab2/semen/sim/tb_automata.sv
`timescale 1ns / 1ns

module tb_automata;
  parameter STATES = 4;
  parameter INPUTS = 4;
  
  logic rst = 0;
  logic clk = 1;
  logic [1:0] i;
  logic [1:0] y;

  initial begin
    $dumpfile("work/wave.vcd");
    $dumpvars(0, tb_automata);
  end
  
  // Тест: полный обход 16 рёбер (Mealy)
  // Выход: y = state ^ i, где state(t) = i(t-1)
  initial begin
    integer total;
    total = 0;

    $display("=== Starting Mealy Automata Test ===");
    $display("Testing all 16 edges: (state, input) -> output");

    // Сброс
    @(posedge clk);
    rst = 1'b1;
    @(posedge clk);
    rst = 1'b0;

    // Обход всех пар (a, b), где a — требуемое состояние, b — текущий вход
    for (int a = 0; a < STATES; a++) begin
      for (int b = 0; b < INPUTS; b++) begin
        logic [1:0] a_bits;
        logic [1:0] b_bits;
        logic [1:0] exp; // ожидаемый Mealy-выход

        a_bits = a[1:0];
        b_bits = b[1:0];
        exp = a_bits ^ b_bits;

        // Подготовка: выставить состояние a (предыдущим входом)
        i = a_bits;
        @(posedge clk); // теперь state == a_bits

        // Применить вход b и проверить выход немедленно (Mealy — комбин.)
        i = b_bits;
        #1; // дать времени комбинационной логике

        $display("Edge from state=%2b with i=%2b: y=%2b, expected=%2b",
                 a_bits, b_bits, y, exp);
        assert (y == exp)
        else $error($sformatf("Wrong output: state=%2b, i=%2b, expected=%2b, got=%2b",
                              a_bits, b_bits, exp, y));
        total++;

        // Тактовый шаг вперёд для стабильности
        @(posedge clk);
      end
    end

    $display("=== ALL %0d EDGES TESTED SUCCESSFULLY! ===", total);
    @(posedge clk);
    $finish;
  end
  
  always #5 clk = ~clk;
  
  automata dut (
    .rst(rst),
    .clk(clk),
    .i (i),
    .y (y)
  );
endmodule

Labs5stYear/hardware_impl_crypto/lab2/semen/sim/work/wave.vcd
$date
	Tue Oct 14 23:25:44 2025
$end
$version
	Icarus Verilog
$end
$timescale
	1ns
$end
$scope module tb_automata $end
$var wire 2 ! y [1:0] $end
$var parameter 32 " INPUTS $end
$var parameter 32 # STATES $end
$var reg 1 $ clk $end
$var reg 2 % i [1:0] $end
$var reg 1 & rst $end
$scope module dut $end
$var wire 1 $ clk $end
$var wire 2 ' i [1:0] $end
$var wire 1 & rst $end
$var wire 2 ( y [1:0] $end
$var parameter 2 ) S0 $end
$var parameter 2 * S1 $end
$var parameter 2 + S2 $end
$var parameter 2 , S3 $end
$var reg 2 - next_state [1:0] $end
$var reg 2 . state [1:0] $end
$upscope $end
$scope begin $unm_blk_4 $end
$var integer 32 / total [31:0] $end
$scope begin $ivl_for_loop0 $end
$var integer 32 0 a [31:0] $end
$scope begin $ivl_for_loop1 $end
$var integer 32 1 b [31:0] $end
$scope begin $unm_blk_6 $end
$var reg 2 2 a_bits [1:0] $end
$var reg 2 3 b_bits [1:0] $end
$var reg 2 4 exp [1:0] $end
$upscope $end
$upscope $end
$upscope $end
$upscope $end
$upscope $end
$enddefinitions $end
$comment Show the parameter values. $end
$dumpall
b11 ,
b10 +
b1 *
b0 )
b100 #
b100 "
$end
#0
$dumpvars
bx 4
bx 3
bx 2
b0 1
b0 0
b0 /
bx .
bx -
bx (
bx '
0&
bx %
1$
bx !
$end
#5
0$
#10
b11 -
b0 .
1&
1$
#15
0$
#20
b0 !
b0 (
b0 -
b0 %
b0 '
b0 4
b0 3
b0 2
0&
1$
#25
0$
#30
1$
#31
b1 /
#35
0$
#40
b1 4
b1 3
b1 1
1$
#45
0$
#50
b1 !
b1 (
b1 -
b1 %
b1 '
1$
#51
b10 /
#55
0$
#60
b1 .
b1 !
b1 (
b0 -
b0 %
b0 '
b10 4
b10 3
b10 1
1$
#65
0$
#70
b0 .
b10 !
b10 (
b10 -
b10 %
b10 '
1$
#71
b11 /
#75
0$
#80
b10 .
b10 !
b10 (
b0 -
b0 %
b0 '
b11 4
b11 3
b11 1
1$
#85
0$
#90
b0 .
b11 !
b11 (
b11 -
b11 %
b11 '
1$
#91
b100 /
#95
0$
#100
b11 .
b10 !
b10 (
b1 -
b1 %
b1 '
b1 4
b0 3
b1 2
b1 0
b0 1
1$
#105
0$
#110
b1 .
b1 !
b1 (
b0 -
b0 %
b0 '
1$
#111
b101 /
#115
0$
#120
b0 .
b1 !
b1 (
b1 -
b1 %
b1 '
b0 4
b1 3
b1 1
1$
#125
0$
#130
b0 !
b0 (
b1 .
1$
#131
b110 /
#135
0$
#140
b11 4
b10 3
b10 1
1$
#145
0$
#150
b11 !
b11 (
b10 -
b10 %
b10 '
1$
#151
b111 /
#155
0$
#160
b10 .
b11 !
b11 (
b1 -
b1 %
b1 '
b10 4
b11 3
b11 1
1$
#165
0$
#170
b1 .
b10 !
b10 (
b11 -
b11 %
b11 '
1$
#171
b1000 /
#175
0$
#180
b11 .
b1 !
b1 (
b10 -
b10 %
b10 '
b0 3
b10 2
b10 0
b0 1
1$
#185
0$
#190
b10 .
b10 !
b10 (
b0 -
b0 %
b0 '
1$
#191
b1001 /
#195
0$
#200
b0 .
b10 !
b10 (
b10 -
b10 %
b10 '
b11 4
b1 3
b1 1
1$
#205
0$
#210
b10 .
b11 !
b11 (
b1 -
b1 %
b1 '
1$
#211
b1010 /
#215
0$
#220
b1 .
b11 !
b11 (
b10 -
b10 %
b10 '
b0 4
b10 3
b10 1
1$
#225
0$
#230
b0 !
b0 (
b10 .
1$
#231
b1011 /
#235
0$
#240
b1 4
b11 3
b11 1
1$
#245
0$
#250
b1 !
b1 (
b11 -
b11 %
b11 '
1$
#251
b1100 /
#255
0$
#260
b0 !
b0 (
b11 .
b11 4
b0 3
b11 2
b11 0
b0 1
1$
#265
0$
#270
b11 !
b11 (
b0 -
b0 %
b0 '
1$
#271
b1101 /
#275
0$
#280
b0 .
b11 !
b11 (
b11 -
b11 %
b11 '
b10 4
b1 3
b1 1
1$
#285
0$
#290
b11 .
b10 !
b10 (
b1 -
b1 %
b1 '
1$
#291
b1110 /
#295
0$
#300
b1 .
b10 !
b10 (
b11 -
b11 %
b11 '
b1 4
b10 3
b10 1
1$
#305
0$
#310
b11 .
b1 !
b1 (
b10 -
b10 %
b10 '
1$
#311
b1111 /
#315
0$
#320
b10 .
b1 !
b1 (
b11 -
b11 %
b11 '
b0 4
b11 3
b11 1
1$
#325
0$
#330
b0 !
b0 (
b11 .
1$
#331
b10000 /
#335
0$
#340
b100 0
b100 1
1$
